AutoBotLibrary/AutoBotLibrary.py
AutoBotLibrary/__init__.py
robotframework_autobotlibrary-1.0.0.dist-info/METADATA
robotframework_autobotlibrary-1.0.0.dist-info/WHEEL
robotframework_autobotlibrary-1.0.0.dist-info/top_level.txt
robotframework_autobotlibrary-1.0.0.dist-info/RECORD
