Metadata-Version: 2.1
Name: robotframework-autobotlibrary
Version: 1.0.0
Summary: Robot Framework library wrapper for PyAutoGUI.
Home-page: https://github.com/deekshith-poojary98/robotframework-autobotlibrary
Author: Deekshith Poojary
Author-email: deekshithpoojary355@gmail.com
Maintainer: Deekshith Poojary
License: BSD-3-Clause License
Keywords: gui desktop testing testautomation robotframework robotframework-autobotlibrary
Platform: UNKNOWN
Classifier: Programming Language :: Python :: 3
Classifier: License :: OSI Approved :: BSD License
Classifier: Operating System :: OS Independent
Classifier: Framework :: Robot Framework :: Library
Classifier: Intended Audience :: Developers
Classifier: Topic :: Software Development :: Testing
Requires-Python: >=3.6
Requires-Dist: PyAutoGUI (==0.9.54)
Requires-Dist: opencv-python
Requires-Dist: robotframework (>=5.0.1)
